tn3270/__about__.py
tn3270/__init__.py
tn3270/attributes.py
tn3270/datastream.py
tn3270/ebcdic.py
tn3270/emulator.py
tn3270/structured_fields.py
tn3270/telnet.py
pytn3270-0.16.0.dist-info/LICENSE
pytn3270-0.16.0.dist-info/METADATA
pytn3270-0.16.0.dist-info/WHEEL
pytn3270-0.16.0.dist-info/top_level.txt
pytn3270-0.16.0.dist-info/RECORD
