Metadata-Version: 2.1
Name: pytn3270
Version: 0.16.0
Summary: TN3270 library
Home-page: https://github.com/lowobservable/pytn3270
Author: Andrew Kay
Author-email: projects@ajk.me
Classifier: Development Status :: 3 - Alpha
Classifier: License :: OSI Approved :: ISC License (ISCL)
Classifier: Operating System :: OS Independent
Classifier: Programming Language :: Python :: 3
Classifier: Topic :: Communications
Classifier: Topic :: Terminals
License-File: LICENSE
Requires-Dist: telnetlib3
